{"vendidos":[{"nombreEvento":"Explicacion json","tipo":"PRINCIPAL","precio":150,"eventoId":0,"id":0,"asiento":0,"direccionRecinto":"dorrego y no se que","fechaYHora":"Viernes 8:30hs"},{"nombreEvento":"Explicacion json","tipo":"PRINCIPAL","precio":150,"eventoId":0,"id":2,"asiento":1,"direccionRecinto":"dorrego y no se que","fechaYHora":"Viernes 8:30hs"}],"eventos":[{"descripcion":"Clase de json","funciones":[{"recinto":{"sectores":[{"tipo":"PRINCIPAL","asientos":[{"numero":0,"disponible":false},{"numero":1,"disponible":false},{"numero":2,"disponible":true},{"numero":3,"disponible":true},{"numero":4,"disponible":true}],"id":0,"nombre":"Labo 3"}],"direccion":"dorrego y no se que","id":0,"nombre":"UTN","capacidad":5},"precioBase":100,"hora":"Viernes 8:30hs","id":0},{"recinto":{"sectores":[{"tipo":"PRINCIPAL","asientos":[{"numero":10,"disponible":true},{"numero":11,"disponible":true},{"numero":12,"disponible":true},{"numero":13,"disponible":true},{"numero":14,"disponible":true},{"numero":15,"disponible":true},{"numero":16,"disponible":true},{"numero":17,"disponible":true},{"numero":18,"disponible":true},{"numero":19,"disponible":true}],"id":2,"nombre":"Aula Magna"}],"direccion":"dorrego y algo","id":2,"nombre":"UTN","capacidad":10},"precioBase":200,"hora":"lunes 20:30","id":2}],"categoria":"CINE","id":0,"nombre":"Explicacion json"},{"descripcion":"quimey ensenia factos","funciones":[],"categoria":"TEATRO","id":0,"nombre":"Teatro de quimey"}],"usuarios":[{"contrasenia":"juan1234","id":0,"nombre":"Juan","eventosCreados":[{"descripcion":"Clase de json","funciones":[{"recinto":{"sectores":[{"tipo":"PRINCIPAL","asientos":[{"numero":0,"disponible":false},{"numero":1,"disponible":true},{"numero":2,"disponible":true},{"numero":3,"disponible":true},{"numero":4,"disponible":true}],"id":0,"nombre":"Labo 3"}],"direccion":"dorrego y no se que","id":0,"nombre":"UTN","capacidad":5},"precioBase":100,"hora":"Viernes 8:30hs","id":0}],"categoria":"CINE","id":0,"nombre":"Explicacion json"},{"descripcion":"quimey ensenia factos","funciones":[],"categoria":"TEATRO","id":0,"nombre":"Teatro de quimey"}],"email":"juan@gmail.com"},{"contrasenia":"quimey123","ticketsVendidos":[{"nombreEvento":"Explicacion json","tipo":"PRINCIPAL","precio":150,"eventoId":0,"id":0,"asiento":0,"direccionRecinto":"dorrego y no se que","fechaYHora":"Viernes 8:30hs"},{"nombreEvento":"Explicacion json","tipo":"PRINCIPAL","precio":150,"eventoId":0,"id":2,"asiento":1,"direccionRecinto":"dorrego y no se que","fechaYHora":"Viernes 8:30hs"}],"id":1,"nombre":"Quimey","email":"quimey@gmail.com"}]}